fastapi_brocaster/__init__.py
fastapi_brocaster/other.py
fastapi_broadcaster-0.0.1.dist-info/LICENSE
fastapi_broadcaster-0.0.1.dist-info/METADATA
fastapi_broadcaster-0.0.1.dist-info/WHEEL
fastapi_broadcaster-0.0.1.dist-info/top_level.txt
fastapi_broadcaster-0.0.1.dist-info/RECORD
