Metadata-Version: 2.1
Name: fastapi-broadcaster
Version: 0.0.1
Summary: websocket using for fastapi channels
Home-page: https://github.com/YGuang233/fastapi-channels
Author: BXZDYG
Author-email: banxingzhedeyangguang@gmail.com
License: MIT
Classifier: Programming Language :: Python :: 3.8
Classifier: Programming Language :: Python :: 3.9
Classifier: Programming Language :: Python :: 3.10
Classifier: Programming Language :: Python :: 3.11
Classifier: License :: OSI Approved :: MIT License
Classifier: Operating System :: OS Independent
Requires-Python: >=3.8
License-File: LICENSE
Requires-Dist: fastapi >=0.110.0
Requires-Dist: broadcaster >=0.3.1
Requires-Dist: fastapi-limiter <=0.1.6
